Workbook
Name Slicer_Region: #N/A

Sheet Raw Dataset
A1: Order ID | B1: Order Date | C1: Customer | D1: Product | E1: Category | F1: Region | G1: Quantity | H1: Sales | I1: Profit
A2: ORD1001 | B2: 45783 | C2: Riya Gupta | D2: Monitor | E2: Electronics | F2: North | G2: 2 | H2: 32400 | I2: 5832
A3: ORD1002 | B3: 45874 | C3: Vikas Jain | D3: Monitor | E3: Electronics | F3: North | G3: 1 | H3: 15300 | I3: 918
A4: ORD1003 | B4: 45966 | C4: Simran Kaur | D4: Keyboard | E4: Electronics | F4: South | G4: 1 | H4: 2625 | I4: 210
A5: ORD1004 | B5: 45887 | C5: Sneha Kapoor | D5: Desk Lamp | E5: Furniture | F5: East | G5: 3 | H5: 7650 | I5: 612
A6: ORD1005 | B6: 45737 | C6: Riya Gupta | D6: Office Table | E6: Furniture | F6: West | G6: 2 | H6: 24000 | I6: 1440
A7: ORD1006 | B7: 45841 | C7: Priya Mehta | D7: Monitor | E7: Electronics | F7: East | G7: 3 | H7: 56700 | I7: 5670
A8: ORD1007 | B8: 45721 | C8: Simran Kaur | D8: Laptop | E8: Electronics | F8: East | G8: 4 | H8: 204000 | I8: 30600
A9: ORD1008 | B9: 45756 | C9: Vikas Jain | D9: Mouse | E9: Electronics | F9: West | G9: 1 | H9: 1275 | I9: 229.5
A10: ORD1009 | B10: 45777 | C10: Priya Mehta | D10: Keyboard | E10: Electronics | F10: West | G10: 1 | H10: 2500 | I10: 250
A11: ORD1010 | B11: 45847 | C11: Amit Verma | D11: Sofa | E11: Furniture | F11: West | G11: 3 | H11: 67500 | I11: 12150
A12: ORD1011 | B12: 45983 | C12: Vikas Jain | D12: Mouse | E12: Electronics | F12: North | G12: 2 | H12: 3150 | I12: 567
A13: ORD1012 | B13: 45852 | C13: Karan Arora | D13: Keyboard | E13: Electronics | F13: South | G13: 3 | H13: 8250 | I13: 1485
... A46: ORD1045 | B46: 45762 | C46: Riya Gupta | D46: Bookshelf | E46: Furniture | F46: West | G46: 3 | H46: 24300 | I46: 2430
A47: ORD1046 | B47: 45892 | C47: Riya Gupta | D47: Office Table | E47: Furniture | F47: South | G47: 3 | I47: 1836
A48: ORD1047 | B48: 45933 | C48: Priya Mehta | D48: Sofa | E48: Furniture | F48: North | G48: 2 | H48: 52500 | I48: 5250
A49: ORD1048 | B49: 45783 | C49: Priya Mehta | D49: Phone | E49: Electronics | F49: West | G49: 3 | H49: 90000 | I49: 7200
A50: ORD1049 | B50: 45992 | C50: Vikas Jain | D50: Sofa | E50: Furniture | F50: West | G50: 1 | H50: 27500 | I50: 4125
A51: ORD1050 | B51: 45793 | C51: Amit Verma | D51: Mouse | E51: Electronics | F51: North | G51: 1 | H51: 1275 | I51: 229.5
A52: ORD1051 | B52: 45802 | C52: Riya Gupta | D52: Desk Lamp | E52: Furniture | F52: South | G52: 2 | H52: 6600 | I52: 660
A53: ORD1052 | B53: 45908 | C53: Simran Kaur | D53: Keyboard | E53: Electronics | F53: West | G53: 3 | H53: 6375 | I53: 382.5
A54: ORD1053 | B54: 45659 | C54: Rahul Sharma | D54: Office Table | E54: Furniture | F54: West | G54: 3 | H54: 32400
A55: ORD1054 | B55: 45940 | C55: Karan Arora | D55: Mouse | E55: Electronics | F55: South | G55: 4 | H55: 6300 | I55: 378
A56: ORD1055 | B56: 45937 | C56: Amit Verma | D56: Monitor | E56: Electronics | F56: North | G56: 1 | H56: 18000 | I56: 2700
A57: ORD1056 | B57: 45723 | C57: Neha Singh | D57: Desk Lamp | E57: Furniture | F57: South | G57: 1 | H57: 3000 | I57: 300
A58: ORD1057 | B58: 46007 | C58: Sneha Kapoor | D58: Laptop | E58: Electronics | F58: West | G58: 2 | H58: 132000 | I58: 7920
A59: ORD1058 | B59: 45737 | C59: Vikas Jain | D59: Office Chair | E59: Furniture | F59: East | G59: 2 | H59: 14400 | I59: 1152
A60: ORD1059 | B60: 45828 | C60: Amit Verma | D60: Office Table | E60: Furniture | F60: North | G60: 4 | H60: 52800 | I60: 9504
A61: ORD1060 | B61: 46017 | C61: Amit Verma | D61: Keyboard | E61: Electronics | F61: West | G61: 1 | H61: 2500 | I61: 150
A62: ORD1061 | B62: 45893 | C62: Sneha Kapoor | D62: Sofa | E62: Furniture | F62: South | G62: 3 | H62: 75000 | I62: 6000
A63: ORD1062 | B63: 45862 | C63: Sneha Kapoor | D63: Keyboard | E63: Electronics | F63: North | G63: 3 | H63: 7500 | I63: 450
A64: ORD1063 | B64: 45862 | C64: Simran Kaur | D64: Mouse | E64: Electronics | F64: West | G64: 3 | H64: 3825 | I64: 229.5
A65: ORD1064 | B65: 45793 | C65: Vikas Jain | D65: Mouse | E65: Electronics | F65: South | G65: 1 | H65: 1275 | I65: 191.25
A66: ORD1065 | B66: 45881 | C66: Arjun Malhotra | D66: Office Table | E66: Furniture | F66: West | G66: 1 | H66: 12000 | I66: 1800
... A123: ORD1075 | B123: 45870 | C123: Karan Arora | D123: Sofa | E123: Furniture | F123: North | G123: 2 | H123: 55000 | I123: 9900

Sheet Cleaned Dataset
A1: Order ID | B1: Order Date | C1: Customer | D1: Product | E1: Category | F1: Region | G1: Quantity | H1: Sales | I1: Profit | O1: Clean Customer | P1: Clean Category | Q1: Clean Region
A2: ORD1001 | B2: 45783 | C2: Riya Gupta | D2: Monitor | E2: Electronics | F2: North | G2: 2 | H2: 32400 | I2: 5832 | O2: =TRIM(C2) -> Riya Gupta | P2: =TRIM(E2) -> Electronics | Q2: =TRIM(F2) -> North
A3: ORD1002 | B3: 45874 | C3: Vikas Jain | D3: Monitor | E3: Electronics | F3: North | G3: 1 | H3: 15300 | I3: 918 | O3: =TRIM(C3) -> Vikas Jain | P3: =TRIM(E3) -> Electronics | Q3: =TRIM(F3) -> North
A4: ORD1003 | B4: 45966 | C4: Simran Kaur | D4: Keyboard | E4: Electronics | F4: South | G4: 1 | H4: 2625 | I4: 210 | O4: =TRIM(C4) -> Simran Kaur | P4: =TRIM(E4) -> Electronics | Q4: =TRIM(F4) -> South
A5: ORD1004 | B5: 45887 | C5: Sneha Kapoor | D5: Desk Lamp | E5: Furniture | F5: East | G5: 3 | H5: 7650 | I5: 612 | O5: =TRIM(C5) -> Sneha Kapoor | P5: =TRIM(E5) -> Furniture | Q5: =TRIM(F5) -> East
A6: ORD1005 | B6: 45737 | C6: Riya Gupta | D6: Office Table | E6: Furniture | F6: West | G6: 2 | H6: 24000 | I6: 1440 | O6: =TRIM(C6) -> Riya Gupta | P6: =TRIM(E6) -> Furniture | Q6: =TRIM(F6) -> West
A7: ORD1006 | B7: 45841 | C7: Priya Mehta | D7: Monitor | E7: Electronics | F7: East | G7: 3 | H7: 56700 | I7: 5670 | O7: =TRIM(C7) -> Priya Mehta | P7: =TRIM(E7) -> Electronics | Q7: =TRIM(F7) -> East
A8: ORD1007 | B8: 45721 | C8: Simran Kaur | D8: Laptop | E8: Electronics | F8: East | G8: 4 | H8: 204000 | I8: 30600 | O8: =TRIM(C8) -> Simran Kaur | P8: =TRIM(E8) -> Electronics | Q8: =TRIM(F8) -> East
A9: ORD1008 | B9: 45756 | C9: Vikas Jain | D9: Mouse | E9: Electronics | F9: West | G9: 1 | H9: 1275 | I9: 229.5 | O9: =TRIM(C9) -> Vikas Jain | P9: =TRIM(E9) -> Electronics | Q9: =TRIM(F9) -> West
A10: ORD1009 | B10: 45777 | C10: Priya Mehta | D10: Keyboard | E10: Electronics | F10: West | G10: 1 | H10: 2500 | I10: 250 | O10: =TRIM(C10) -> Priya Mehta | P10: =TRIM(E10) -> Electronics | Q10: =TRIM(F10) -> West
A11: ORD1010 | B11: 45847 | C11: Amit Verma | D11: Sofa | E11: Furniture | F11: West | G11: 3 | H11: 67500 | I11: 12150 | O11: =TRIM(C11) -> Amit Verma | P11: =TRIM(E11) -> Furniture | Q11: =TRIM(F11) -> West
A12: ORD1011 | B12: 45983 | C12: Vikas Jain | D12: Mouse | E12: Electronics | F12: North | G12: 2 | H12: 3150 | I12: 567 | O12: =TRIM(C12) -> Vikas Jain | P12: =TRIM(E12) -> Electronics | Q12: =TRIM(F12) -> North
A13: ORD1012 | B13: 45852 | C13: Karan Arora | D13: Keyboard | E13: Electronics | F13: South | G13: 3 | H13: 8250 | I13: 1485 | O13: =TRIM(C13) -> Karan Arora | P13: =TRIM(E13) -> Electronics | Q13: =TRIM(F13) -> South
... A46: ORD1045 | B46: 45762 | C46: Riya Gupta | D46: Bookshelf | E46: Furniture | F46: West | G46: 3 | H46: 24300 | I46: 2430 | O46: =TRIM(C46) -> Riya Gupta | P46: =TRIM(E46) -> Furniture | Q46: =TRIM(F46) -> West
A47: ORD1046 | B47: 45892 | C47: Riya Gupta | D47: Office Table | E47: Furniture | F47: South | G47: 3 | I47: 1836 | O47: =TRIM(C47) -> Riya Gupta | P47: =TRIM(E47) -> Furniture | Q47: =TRIM(F47) -> South
A48: ORD1047 | B48: 45933 | C48: Priya Mehta | D48: Sofa | E48: Furniture | F48: North | G48: 2 | H48: 52500 | I48: 5250 | O48: =TRIM(C48) -> Priya Mehta | P48: =TRIM(E48) -> Furniture | Q48: =TRIM(F48) -> North
A49: ORD1048 | B49: 45783 | C49: Priya Mehta | D49: Phone | E49: Electronics | F49: West | G49: 3 | H49: 90000 | I49: 7200 | O49: =TRIM(C49) -> Priya Mehta | P49: =TRIM(E49) -> Electronics | Q49: =TRIM(F49) -> West
A50: ORD1049 | B50: 45992 | C50: Vikas Jain | D50: Sofa | E50: Furniture | F50: West | G50: 1 | H50: 27500 | I50: 4125 | O50: =TRIM(C50) -> Vikas Jain | P50: =TRIM(E50) -> Furniture | Q50: =TRIM(F50) -> West
A51: ORD1050 | B51: 45793 | C51: Amit Verma | D51: Mouse | E51: Electronics | F51: North | G51: 1 | H51: 1275 | I51: 229.5 | O51: =TRIM(C51) -> Amit Verma | P51: =TRIM(E51) -> Electronics | Q51: =TRIM(F51) -> North
A52: ORD1051 | B52: 45802 | C52: Riya Gupta | D52: Desk Lamp | E52: Furniture | F52: South | G52: 2 | H52: 6600 | I52: 660 | L52: =ISNUMBER(H2) -> TRUE | O52: =TRIM(C52) -> Riya Gupta | P52: =TRIM(E52) -> Furniture | Q52: =TRIM(F52) -> South
A53: ORD1052 | B53: 45908 | C53: Simran Kaur | D53: Keyboard | E53: Electronics | F53: West | G53: 3 | H53: 6375 | I53: 382.5 | L53: =ISNUMBER(I2) -> TRUE | O53: =TRIM(C53) -> Simran Kaur | P53: =TRIM(E53) -> Electronics | Q53: =TRIM(F53) -> West
A54: ORD1053 | B54: 45659 | C54: Rahul Sharma | D54: Office Table | E54: Furniture | F54: West | G54: 3 | H54: 32400 | O54: =TRIM(C54) -> Rahul Sharma | P54: =TRIM(E54) -> Furniture | Q54: =TRIM(F54) -> West
A55: ORD1054 | B55: 45940 | C55: Karan Arora | D55: Mouse | E55: Electronics | F55: South | G55: 4 | H55: 6300 | I55: 378 | O55: =TRIM(C55) -> Karan Arora | P55: =TRIM(E55) -> Electronics | Q55: =TRIM(F55) -> South
A56: ORD1055 | B56: 45937 | C56: Amit Verma | D56: Monitor | E56: Electronics | F56: North | G56: 1 | H56: 18000 | I56: 2700 | O56: =TRIM(C56) -> Amit Verma | P56: =TRIM(E56) -> Electronics | Q56: =TRIM(F56) -> North
A57: ORD1056 | B57: 45723 | C57: Neha Singh | D57: Desk Lamp | E57: Furniture | F57: South | G57: 1 | H57: 3000 | I57: 300 | O57: =TRIM(C57) -> Neha Singh | P57: =TRIM(E57) -> Furniture | Q57: =TRIM(F57) -> South
A58: ORD1057 | B58: 46007 | C58: Sneha Kapoor | D58: Laptop | E58: Electronics | F58: West | G58: 2 | H58: 132000 | I58: 7920 | O58: =TRIM(C58) -> Sneha Kapoor | P58: =TRIM(E58) -> Electronics | Q58: =TRIM(F58) -> West
A59: ORD1058 | B59: 45737 | C59: Vikas Jain | D59: Office Chair | E59: Furniture | F59: East | G59: 2 | H59: 14400 | I59: 1152 | O59: =TRIM(C59) -> Vikas Jain | P59: =TRIM(E59) -> Furniture | Q59: =TRIM(F59) -> East
A60: ORD1059 | B60: 45828 | C60: Amit Verma | D60: Office Table | E60: Furniture | F60: North | G60: 4 | H60: 52800 | I60: 9504 | O60: =TRIM(C60) -> Amit Verma | P60: =TRIM(E60) -> Furniture | Q60: =TRIM(F60) -> North
A61: ORD1060 | B61: 46017 | C61: Amit Verma | D61: Keyboard | E61: Electronics | F61: West | G61: 1 | H61: 2500 | I61: 150 | O61: =TRIM(C61) -> Amit Verma | P61: =TRIM(E61) -> Electronics | Q61: =TRIM(F61) -> West
A62: ORD1061 | B62: 45893 | C62: Sneha Kapoor | D62: Sofa | E62: Furniture | F62: South | G62: 3 | H62: 75000 | I62: 6000 | O62: =TRIM(C62) -> Sneha Kapoor | P62: =TRIM(E62) -> Furniture | Q62: =TRIM(F62) -> South
A63: ORD1062 | B63: 45862 | C63: Sneha Kapoor | D63: Keyboard | E63: Electronics | F63: North | G63: 3 | H63: 7500 | I63: 450 | O63: =TRIM(C63) -> Sneha Kapoor | P63: =TRIM(E63) -> Electronics | Q63: =TRIM(F63) -> North
A64: ORD1063 | B64: 45862 | C64: Simran Kaur | D64: Mouse | E64: Electronics | F64: West | G64: 3 | H64: 3825 | I64: 229.5 | O64: =TRIM(C64) -> Simran Kaur | P64: =TRIM(E64) -> Electronics | Q64: =TRIM(F64) -> West
A65: ORD1064 | B65: 45793 | C65: Vikas Jain | D65: Mouse | E65: Electronics | F65: South | G65: 1 | H65: 1275 | I65: 191.25 | O65: =TRIM(C65) -> Vikas Jain | P65: =TRIM(E65) -> Electronics | Q65: =TRIM(F65) -> South
A66: ORD1065 | B66: 45881 | C66: Arjun Malhotra | D66: Office Table | E66: Furniture | F66: West | G66: 1 | H66: 12000 | I66: 1800 | O66: =TRIM(C66) -> Arjun Malhotra | P66: =TRIM(E66) -> Furniture | Q66: =TRIM(F66) -> West
... A121: ORD1120 | B121: 45785 | C121: Priya Mehta | D121: Bookshelf | E121: Furniture | F121: West | G121: 1 | H121: 9450 | I121: 1134 | O121: =TRIM(C121) -> Priya Mehta | P121: =TRIM(E121) -> Furniture | Q121: =TRIM(F121) -> West

Sheet Cleaning Log 
A1: Issue | B1: Location | C1: Action Taken | D1: Reason
A2: Duplicate records | B2: 2 duplicate rows | C2: Removed | D2: Exact duplicate transactions
A3: Missing Sales | B3: ORD1046 | C3: Kept blank & flagged | D3: True value cannot be reliably derived
A4: Missing Profit | B4: ORD1053 | C4: Kept blank & flagged | D4: True value cannot be reliably derived
A5: Extra spaces | B5: Customer/Category/Region | C5: Applied TRIM to remove leading/trailing spaces | D5: To standardize text and prevent matching/filtering errors
A6: Incorrect/general data types | B6: Order Date, Quantity, Sales, Profit | C6: Converted to appropriate data types | D6: To ensure accurate calculations, sorting and analysis

Sheet Analysis
D1: RETAIL SALES & PROFITABILITY ANALYSIS
B3: TOTAL SALES | C3: TOTAL PROFIT | D3: TOTAL ORDERS | E3: AVERAGE ORDER VALUE | F3: PROFIT MARGIN
B4: =SUM('Cleaned Dataset'!H2:H121) -> 4826425 | C4: =SUM('Cleaned Dataset'!I2:I121) -> 571987.25 | D4: =COUNTA('Cleaned Dataset'!A2:A121) -> 120 | E4: =B4/D4 -> 40220.208 | F4: =C4/B4 -> 0.11851158
A6: # | B6: Business Insight | C6: Evidence / Analysis | D6: Recommended Action
A7: 1 | B7: Laptop is the strongest product performer. | C7: Laptop leads total sales and total profit, making it the strongest overall contributor. | D7: Protect availability, maintain competitive pricing, and explore opportunities to scale demand.
A8: 2 | B8: Monitor represents a potential growth opportunity. | C8: Monitor has a relatively strong profit margin but comparatively lower sales. | D8: Investigate demand drivers and test targeted promotions while protecting margin.
A9: 3 | B9: Office Chair requires profitability investigation. | C9: Office Chair has the lowest profit margin despite generating reasonable sales. | D9: Review pricing, discounts, sourcing/acquisition costs, and product profitability.
A10: 4 | B10: North is the strongest region overall. | C10: North records the highest total sales and profit; strong Furniture sales are a major contributor. | D10: Maintain momentum and identify successful practices that can be replicated elsewhere.
A11: 5 | B11: South is the weakest-performing region. | C11: South has the lowest overall sales and profit, with particularly weak Electronics sales. | D11: Investigate local demand, product mix, pricing, and promotional effectiveness.
A12: 6 | B12: Electronics is the strongest category. | C12: Electronics generates the highest total sales and profit; East leads Electronics sales. | D12: Protect performance and study successful regional/product patterns for growth.
A13: 7 | B13: Furniture is the key category requiring improvement. | C13: Furniture has the lowest total sales and profit, although North performs strongly in Furniture. | D13: Identify underperforming products and test targeted pricing, promotion, and assortment strategies.
A14: 8 | B14: Sales performance is highly volatile across months. | C14: May records the highest sales and profit, while September records the lowest. | D14: Investigate the drivers of May's peak and September's decline for better planning.
A15: 9 | B15: Priya Mehta is a particularly valuable customer. | C15: Priya Mehta has the highest total sales and profit and a high order frequency. | D15: Prioritize retention, personalized engagement, and cross-sell opportunities.
A16: 10 | B16: Data quality must be considered in financial reporting. | C16: ORD1046 has missing Sales and ORD1053 has missing Profit; values were not imputed without reliable evidence. | D16: Flag incomplete transactions and validate source records before high-stakes decisions.
A18: EXECUTIVE TAKEAWAY
A19: The business is driven by strong Electronics performance and high-performing products such as Laptop, while North is the strongest region overall. Key opportunities are improving South and Furniture performance, investigating Office Chair's weak margin, and scaling high-margin products such as Monitor. Management should prioritize sustainable growth rather than blanket discounting.
A23: Methodology: | B23: Insights are based on the cleaned retail dataset and Pivot Table analysis covering region, category, product, customer, and monthly performance.

Sheet Dashboard
E1: Retail Sales & Profitability Dashboard
B4: TOTAL SALES | D4: TOTAL PROFIT | F4: TOTAL ORDERS | H4: AVERAGE ORDER VALUE | J4: PROFIT MARGIN
B5: =Analysis!B4 -> 4826425 | D5: =Analysis!C4 -> 571987.25 | F5: =Analysis!D4 -> 120 | H5: =Analysis!E4 -> 40220.208 | J5: =Analysis!F4 -> 0.11851158
C24: Monthly Sales and Profit Trend | H24: Regional Sales & Profit Performance
C48: Category Sales & Profit Performance | H48: Top 5 Products by Profit

Sheet Pivot Analysis
A1: Row Labels | B1: Sum of Sales | C1: Sum of Profit | E1: Row Labels | F1: Sum of Profit | G1: Sum of Sales | I1: Row Labels | J1: Sum of Quantity | K1: Sum of Sales | L1: Sum of Profit | N1: Row Labels | O1: Count of Order ID | P1: Sum of Sales | Q1: Sum of Profit
A2: East | B2: 1416375 | C2: 163617 | E2: Electronics | F2: 330934.25 | G2: 2807175 | I2: Bookshelf | J2: 22 | K2: 194400 | L2: 22167 | N2: Amit Verma | O2: 9 | P2: 262975 | Q2: 33184.5
A3: North | B3: 1451175 | C3: 182631 | E3: Furniture | F3: 241053 | G3: 2019250 | I3: Desk Lamp | J3: 31 | K3: 87900 | L3: 9816 | N3: Rahul Sharma | O3: 7 | P3: 327100 | Q3: 30255
A4: South | B4: 597175 | C4: 69363.25 | E4: Grand Total | F4: 571987.25 | G4: 4826425 | I4: Keyboard | J4: 34 | K4: 83625 | L4: 11007.5 | N4: Sneha Kapoor | O4: 12 | P4: 374900 | Q4: 27160.5
A5: West | B5: 1361700 | C5: 156376 | F5: PT2 — Category Performance | I5: Laptop | J5: 26 | K5: 1536000 | L5: 179430 | N5: Vikas Jain | O5: 16 | P5: 386375 | Q5: 50616.75
A6: Grand Total | B6: 4826425 | C6: 571987.25 | I6: Monitor | J6: 26 | K6: 460800 | L6: 62586 | N6: Karan Arora | O6: 12 | P6: 477950 | Q6: 61824
B7: PT1 — Regional Performance | I7: Mouse | J7: 32 | K7: 46350 | L7: 4866.75 | N7: Arjun Malhotra | O7: 9 | P7: 492175 | Q7: 55792.5
I8: Office Chair | J8: 18 | K8: 138800 | L8: 13584 | N8: Neha Singh | O8: 10 | P8: 510525 | Q8: 50332
A9: Row Labels | B9: Sum of Sales | C9: Sum of Profit | I9: Office Table | J9: 35 | K9: 391800 | L9: 59130 | N9: Riya Gupta | O9: 15 | P9: 611400 | Q9: 84294
A10: Jan | B10: 604825 | C10: 70911 | I10: Phone | J10: 22 | K10: 648000 | L10: 71100 | N10: Simran Kaur | O10: 16 | P10: 615975 | Q10: 85482
A11: Feb | B11: 249600 | C11: 33714 | I11: Sofa | J11: 50 | K11: 1238750 | L11: 138300 | N11: Priya Mehta | O11: 14 | P11: 767050 | Q11: 93046
A12: Mar | B12: 391675 | C12: 47844 | I12: Grand Total | J12: 296 | K12: 4826425 | L12: 571987.25 | N12: Grand Total | O12: 120 | P12: 4826425 | Q12: 571987.25
A13: Apr | B13: 572550 | C13: 79273 | J13: PT3 — Product Performance | O13: PT4 — Customer Performance
A14: May | B14: 637800 | C14: 82340.75
A15: Jun | B15: 293500 | C15: 37257 | I15: Sum of Sales | J15: Column Labels | N15: Row Labels | O15: Sum of Sales | P15: Sum of Profit | Q15: Product Margin
A16: Jul | B16: 580025 | C16: 59300.5 | I16: Row Labels | J16: Electronics | K16: Furniture | L16: Grand Total | N16: Bookshelf | O16: 194400 | P16: 22167 | Q16: =GETPIVOTDATA("Sum of Profit",$N$15,"Product","Bookshelf")/GETPIVOTDATA("Sum of Sales",$N$15,"Product","Bookshelf") -> 0.11402778
A17: Aug | B17: 337950 | C17: 42196 | I17: East | J17: 1029225 | K17: 387150 | L17: 1416375 | N17: Desk Lamp | O17: 87900 | P17: 9816 | Q17: =GETPIVOTDATA("Sum of Profit",$N$15,"Product","Desk Lamp")/GETPIVOTDATA("Sum of Sales",$N$15,"Product","Desk Lamp") -> 0.11167235
A18: Sep | B18: 192525 | C18: 17272.5 | I18: North | J18: 755175 | K18: 696000 | L18: 1451175 | N18: Keyboard | O18: 83625 | P18: 11007.5 | Q18: =GETPIVOTDATA("Sum of Profit",$N$15,"Product","Keyboard")/GETPIVOTDATA("Sum of Sales",$N$15,"Product","Keyboard") -> 0.1316293
A19: Oct | B19: 303950 | C19: 38863.5 | I19: South | J19: 283775 | K19: 313400 | L19: 597175 | N19: Laptop | O19: 1536000 | P19: 179430 | Q19: =GETPIVOTDATA("Sum of Profit",$N$15,"Product","Laptop")/GETPIVOTDATA("Sum of Sales",$N$15,"Product","Laptop") -> 0.11681641
A20: Nov | B20: 201375 | C20: 25383 | I20: West | J20: 739000 | K20: 622700 | L20: 1361700 | N20: Monitor | O20: 460800 | P20: 62586 | Q20: =GETPIVOTDATA("Sum of Profit",$N$15,"Product","Monitor")/GETPIVOTDATA("Sum of Sales",$N$15,"Product","Monitor") -> 0.13582031
A21: Dec | B21: 460650 | C21: 37632 | I21: Grand Total | J21: 2807175 | K21: 2019250 | L21: 4826425 | N21: Mouse | O21: 46350 | P21: 4866.75 | Q21: =GETPIVOTDATA("Sum of Profit",$N$15,"Product","Mouse")/GETPIVOTDATA("Sum of Sales",$N$15,"Product","Mouse") -> 0.105
A22: Grand Total | B22: 4826425 | C22: 571987.25 | J22: PT6 — Regional Category Performance | N22: Office Chair | O22: 138800 | P22: 13584 | Q22: =GETPIVOTDATA("Sum of Profit",$N$15,"Product","Office Chair")/GETPIVOTDATA("Sum of Sales",$N$15,"Product","Office Chair") -> 0.097867435
B23: PT5 — Monthly Performance | N23: Office Table | O23: 391800 | P23: 59130 | Q23: =GETPIVOTDATA("Sum of Profit",$N$15,"Product","Office Table")/GETPIVOTDATA("Sum of Sales",$N$15,"Product","Office Table") -> 0.15091884
N24: Phone | O24: 648000 | P24: 71100 | Q24: =GETPIVOTDATA("Sum of Profit",$N$15,"Product","Phone")/GETPIVOTDATA("Sum of Sales",$N$15,"Product","Phone") -> 0.10972222
A25: Row Labels | B25: Sum of Profit | C25: Sum of Sales | D25: Product Margin | F25: Row Labels | G25: Sum of Profit | N25: Sofa | O25: 1238750 | P25: 138300 | Q25: =GETPIVOTDATA("Sum of Profit",$N$15,"Product","Sofa")/GETPIVOTDATA("Sum of Sales",$N$15,"Product","Sofa") -> 0.1116448
A26: Laptop | B26: 179430 | C26: 1536000 | D26: =GETPIVOTDATA("Sum of Profit",$N$15,"Product","Bookshelf")/GETPIVOTDATA("Sum of Sales",$N$15,"Product","Bookshelf") -> 0.11402778 | F26: Laptop | G26: 179430 | N26: Grand Total | O26: 4826425 | P26: 571987.25 | Q26: =GETPIVOTDATA("Sum of Profit",$N$15)/GETPIVOTDATA("Sum of Sales",$N$15) -> 0.11851158
A27: Sofa | B27: 138300 | C27: 1238750 | D27: =GETPIVOTDATA("Sum of Profit",$N$15,"Product","Desk Lamp")/GETPIVOTDATA("Sum of Sales",$N$15,"Product","Desk Lamp") -> 0.11167235 | F27: Sofa | G27: 138300 | O27: PT7 — Product Profitability
A28: Phone | B28: 71100 | C28: 648000 | D28: =GETPIVOTDATA("Sum of Profit",$N$15,"Product","Keyboard")/GETPIVOTDATA("Sum of Sales",$N$15,"Product","Keyboard") -> 0.1316293 | F28: Phone | G28: 71100
A29: Monitor | B29: 62586 | C29: 460800 | D29: =GETPIVOTDATA("Sum of Profit",$N$15,"Product","Laptop")/GETPIVOTDATA("Sum of Sales",$N$15,"Product","Laptop") -> 0.11681641 | F29: Monitor | G29: 62586
A30: Office Table | B30: 59130 | C30: 391800 | D30: =GETPIVOTDATA("Sum of Profit",$N$15,"Product","Monitor")/GETPIVOTDATA("Sum of Sales",$N$15,"Product","Monitor") -> 0.13582031 | F30: Office Table | G30: 59130
A31: Bookshelf | B31: 22167 | C31: 194400 | D31: =GETPIVOTDATA("Sum of Profit",$N$15,"Product","Mouse")/GETPIVOTDATA("Sum of Sales",$N$15,"Product","Mouse") -> 0.105 | F31: Grand Total | G31: 510546
A32: Office Chair | B32: 13584 | C32: 138800 | D32: =GETPIVOTDATA("Sum of Profit",$N$15,"Product","Office Chair")/GETPIVOTDATA("Sum of Sales",$N$15,"Product","Office Chair") -> 0.097867435 | F32: PT9 — Top 5 Products by Profit
A33: Keyboard | B33: 11007.5 | C33: 83625 | D33: =GETPIVOTDATA("Sum of Profit",$N$15,"Product","Office Table")/GETPIVOTDATA("Sum of Sales",$N$15,"Product","Office Table") -> 0.15091884
A34: Desk Lamp | B34: 9816 | C34: 87900 | D34: =GETPIVOTDATA("Sum of Profit",$N$15,"Product","Phone")/GETPIVOTDATA("Sum of Sales",$N$15,"Product","Phone") -> 0.10972222
A35: Mouse | B35: 4866.75 | C35: 46350 | D35: =GETPIVOTDATA("Sum of Profit",$N$15,"Product","Sofa")/GETPIVOTDATA("Sum of Sales",$N$15,"Product","Sofa") -> 0.1116448
A36: Grand Total | B36: 571987.25 | C36: 4826425 | D36: =GETPIVOTDATA("Sum of Profit",$N$15)/GETPIVOTDATA("Sum of Sales",$N$15) -> 0.11851158
B37: PT8 — Product Profit Ranking
